{
  "generator-jhipster": {
    "promptValues": {
      "packageName": "com.alienlab.catpower",
      "nativeLanguage": "zh-cn"
    },
    "jhipsterVersion": "4.5.1",
    "baseName": "catpowerserver",
    "packageName": "com.alienlab.catpower",
    "packageFolder": "com/alienlab/catpower",
    "serverPort": "8080",
    "authenticationType": "jwt",
    "hibernateCache": "no",
    "clusteredHttpSession": false,
    "websocket": false,
    "databaseType": "sql",
    "devDatabaseType": "mysql",
    "prodDatabaseType": "mysql",
    "searchEngine": false,
    "messageBroker": false,
    "serviceDiscoveryType": false,
    "buildTool": "maven",
    "enableSocialSignIn": false,
    "jwtSecretKey": "995dbf604cb52f5ab6312f073d80cb428873d8ba",
    "clientFramework": "angular1",
    "useSass": false,
    "clientPackageManager": "yarn",
    "applicationType": "monolith",
    "testFrameworks": [],
    "jhiPrefix": "jhi",
    "enableTranslation": true,
    "nativeLanguage": "zh-cn",
    "languages": [
      "zh-cn",
      "en"
    ]
  }
}